Workbook

Sheet 00 Summary
C2: ValueBridge | Financial Summary & Scenarios
C3: ValueBridge revenue consists of fees only; sales proceeds collected on behalf of brands are not recognised as revenue. Figures below update with the selections on 08 Scenarios.
C4: Active scenario | E4: =IF(LEN(IF(OR('08 Scenarios'!J9="Conservative",'08 Scenarios'!J9="Optimistic"),TRIM(MID('08 Scenarios'!C8,5,99))&" - "&'08 Scenarios'!J9&"; ","")&IF(OR('08 Scenarios'!J15="Conservative",'08 Scenarios'!J15="Optimistic"),TRIM(MID('08 Scenarios'!C14,5,99))&" - "&'08 Scenarios'!J15&"; ","")&IF(OR('08 Scenarios'!J21="Conservative",'08 Scenarios'!J21="Optimistic"),TRIM(MID('08 Scenarios'!C20,5,99))&" - "&'08 Scenarios'!J21&"; ","")&IF(OR('08 Scenarios'!J27="Conservative",'08 Scenarios'!J27="Optimistic"),TRIM(MID('08 Scenarios'!C26,5,99))&" - "&'08 Scenarios'!J27&"; ","")&IF(OR('08 Scenarios'!J33="Conservative",'08 Scenarios'!J33="Optimistic"),TRIM(MID('08 Scenarios'!C32,5,99))&" - "&'08 Scenarios'!J33&"; ","")&IF(OR('08 Scenarios'!J39="Conservative",'08 Scenarios'!J39="Optimistic"),TRIM(MID('08 Scenarios'!C38,5,99))&" - "&'08 Scenarios'!J39&"; ","")&IF(OR('08 Scenarios'!J45="Conservative",'08 Scenarios'!J45="Optimistic"),TRIM(MID('08 Scenarios'!C44,5,99))&" - "&'08 Scenarios'!J45&"; ","")&IF(OR('08 Scenarios'!J51="Conservative",'08 Scenarios'!J51="Optimistic"),TRIM(MID('08 Scenarios'!C50,5,99))&" - "&'08 Scenarios'!J51&"; ",""))=0,"Base",LEFT(IF(OR('08 Scenarios'!J9="Conservative",'08 Scenarios'!J9="Optimistic"),TRIM(MID('08 Scenarios'!C8,5,99))&" - "&'08 Scenarios'!J9&"; ","")&IF(OR('08 Scenarios'!J15="Conservative",'08 Scenarios'!J15="Optimistic"),TRIM(MID('08 Scenarios'!C14,5,99))&" - "&'08 Scenarios'!J15&"; ","")&IF(OR('08 Scenarios'!J21="Conservative",'08 Scenarios'!J21="Optimistic"),TRIM(MID('08 Scenarios'!C20,5,99))&" - "&'08 Scenarios'!J21&"; ","")&IF(OR('08 Scenarios'!J27="Conservative",'08 Scenarios'!J27="Optimistic"),TRIM(MID('08 Scenarios'!C26,5,99))&" - "&'08 Scenarios'!J27&"; ","")&IF(OR('08 Scenarios'!J33="Conservative",'08 Scenarios'!J33="Optimistic"),TRIM(MID('08 Scenarios'!C32,5,99))&" - "&'08 Scenarios'!J33&"; ","")&IF(OR('08 Scenarios'!J39="Conservative",'08 Scenarios'!J39="Optimistic"),TRIM(MID('08 Scenarios'!C38,5,99))&" - "&'08 Scenarios'!J39&"; ","")&IF(OR('08 Scenarios'!J45="Conservative",'08 Scenarios'!J45="Optimistic"),TRIM(MID('08 Scenarios'!C44,5,99))&" - "&'08 Scenarios'!J45&"; ","")&IF(OR('08 Scenarios'!J51="Conservative",'08 Scenarios'!J51="Optimistic"),TRIM(MID('08 Scenarios'!C50,5,99))&" - "&'08 Scenarios'!J51&"; ",""),LEN(IF(OR('08 Scenarios'!J9="Conservative",'08 Scenarios'!J9="Optimistic"),TRIM(MID('08 Scenarios'!C8,5,99))&" - "&'08 Scenarios'!J9&"; ","")&IF(OR('08 Scenarios'!J15="Conservative",'08 Scenarios'!J15="Optimistic"),TRIM(MID('08 Scenarios'!C14,5,99))&" - "&'08 Scenarios'!J15&"; ","")&IF(OR('08 Scenarios'!J21="Conservative",'08 Scenarios'!J21="Optimistic"),TRIM(MID('08 Scenarios'!C20,5,99))&" - "&'08 Scenarios'!J21&"; ","")&IF(OR('08 Scenarios'!J27="Conservative",'08 Scenarios'!J27="Optimistic"),TRIM(MID('08 Scenarios'!C26,5,99))&" - "&'08 Scenarios'!J27&"; ","")&IF(OR('08 Scenarios'!J33="Conservative",'08 Scenarios'!J33="Optimistic"),TRIM(MID('08 Scenarios'!C32,5,99))&" - "&'08 Scenarios'!J33&"; ","")&IF(OR('08 Scenarios'!J39="Conservative",'08 Scenarios'!J39="Optimistic"),TRIM(MID('08 Scenarios'!C38,5,99))&" - "&'08 Scenarios'!J39&"; ","")&IF(OR('08 Scenarios'!J45="Conservative",'08 Scenarios'!J45="Optimistic"),TRIM(MID('08 Scenarios'!C44,5,99))&" - "&'08 Scenarios'!J45&"; ","")&IF(OR('08 Scenarios'!J51="Conservative",'08 Scenarios'!J51="Optimistic"),TRIM(MID('08 Scenarios'!C50,5,99))&" - "&'08 Scenarios'!J51&"; ",""))-2)) -> Base
C5: Adjust on sheet 08 Scenarios
C7: Line item | D7: Unit | E7: 2027 | F7: 2028 | G7: 2029 | H7: 2030 | J7: Notes
C10: 01 KEY RESULTS
C11: Net revenue | D11: USD | E11: ='05 P&L'!E17 -> 1037817.6 | F11: ='05 P&L'!F17 -> 7351230.8 | G11: ='05 P&L'!G17 -> 17984967 | H11: ='05 P&L'!H17 -> 27198190
C12: EBITDA | D12: USD | E12: ='05 P&L'!E35 -> 743211.14 | F12: ='05 P&L'!F35 -> 6363629.6 | G12: ='05 P&L'!G35 -> 15947231 | H12: ='05 P&L'!H35 -> 24306234
C13: EBITDA margin | D13: % | E13: ='05 P&L'!E36 -> 0.71612886 | F13: ='05 P&L'!F36 -> 0.86565499 | G13: ='05 P&L'!G36 -> 0.88669785 | H13: ='05 P&L'!H36 -> 0.89367103
C14: Cumulative FCF from 2027 | D14: USD | E14: ='06 Cash Flow'!E41 -> 427598.12 | F14: ='06 Cash Flow'!F41 -> 5103182.6 | G14: ='06 Cash Flow'!G41 -> 16658400 | H14: ='06 Cash Flow'!H41 -> 35213428
C16: 02 REVENUE MIX
C17: Gain-share success fee | D17: USD | E17: ='05 P&L'!E11 -> 803784 | F17: ='05 P&L'!F11 -> 4766885.7 | G17: ='05 P&L'!G11 -> 11163667 | H17: ='05 P&L'!H11 -> 16790155
C18: Program subscription fee | D18: USD | E18: ='05 P&L'!E12 -> 27000 | F18: ='05 P&L'!F12 -> 1281000 | G18: ='05 P&L'!G12 -> 3750000 | H18: ='05 P&L'!H12 -> 5640000
C19: Value-added services | D19: USD | E19: ='05 P&L'!E13 -> 134820 | F19: ='05 P&L'!F13 -> 799557.5 | G19: ='05 P&L'!G13 -> 1872500 | H19: ='05 P&L'!H13 -> 2816240
C20: Buyer fees | D20: USD | E20: ='05 P&L'!E16 -> 72213.6 | F20: ='05 P&L'!F16 -> 503787.6 | G20: ='05 P&L'!G16 -> 1198800 | H20: ='05 P&L'!H16 -> 1951795.2
C21: Subscription fee share of net revenue | D21: % | E21: =IF(E11=0,0,E18/E11) -> 0.026016132 | F21: =IF(F11=0,0,F18/F11) -> 0.17425653 | G21: =IF(G11=0,0,G18/G11) -> 0.20850748 | H21: =IF(H11=0,0,H18/H11) -> 0.20736674 | J21: Ratio = program subscription fee / net revenue; does not represent all cash collected before sale.
C23: 03 KEY DRIVERS
C24: Active brands at year-end | D24: brands | E24: ='01 Market'!E15 -> 60 | F24: ='01 Market'!F15 -> 367 | G24: ='01 Market'!G15 -> 633 | H24: ='01 Market'!H15 -> 871 | J24: Includes Vietnam brands, non-OnPoint brands and Thailand brands via CREA.
C25: Net recovery / brand-year | D25: USD | E25: ='01 Market'!E24 -> 89880 | F25: ='01 Market'!F24 -> 149800 | G25: ='01 Market'!G24 -> 149800 | H25: ='01 Market'!H24 -> 149800
C26: Total net recovery processed (not revenue) | D26: USD | E26: ='04 Operations'!E10 -> 5392800 | F26: ='04 Operations'!F10 -> 31982300 | G26: ='04 Operations'!G10 -> 74900000 | H26: ='04 Operations'!H10 -> 112649600
C27: Net revenue / net recovery | D27: % | E27: ='05 P&L'!E18 -> 0.19244504 | F27: ='05 P&L'!F18 -> 0.2298531 | G27: ='05 P&L'!G18 -> 0.24011972 | H27: ='05 P&L'!H18 -> 0.24144063
C30: 04 TARGETS & STATUS
C31: FY2030 net revenue ≥ USD 20 million | D31: status | H31: =IF(H11>=20000000,"PASS","NOT MET") -> PASS
C32: FY2030 net revenue ≥ USD 25 million (reference milestone) | D32: status | H32: =IF(H11>=25000000,"PASS","NOT MET") -> PASS
C33: Positive 2030 EBITDA (on current cost base) | D33: status | H33: =IF(H12>0,"PASS","NOT MET") -> PASS
C34: Model checks | D34: status | E34: ='09 Checks'!E23 -> PASS | F34: ='09 Checks'!F23 -> PASS | G34: ='09 Checks'!G23 -> PASS | H34: ='09 Checks'!H23 -> PASS
C35: Year cumulative FCF turns non-negative | D35: year | E35: ='06 Cash Flow'!E43 -> 2027
C36: Peak funding requirement (based on year-end balances) | D36: USD | E36: ='06 Cash Flow'!E42 -> 0

Sheet 01 Market
C2: ValueBridge | Market, Brands & Volume
C3: Gain-share model · Nominal USD · Fiscal year = calendar year · Volume is NET RECOVERY (after channel costs), not ValueBridge revenue
C5: Line item | D5: Unit | E5: 2027 | F5: 2028 | G5: 2029 | H5: 2030 | J5: Notes
C7: 01 SELLING PERIOD
C8: Selling months in the year | D8: months | E8: 6 | F8: 12 | G8: 12 | H8: 12 | J8: 2027 has 6 revenue-generating months (assumed Jul–Dec); full 12-month operation from 2028.
C10: 02 ACTIVE BRANDS AT YEAR-END BY GROUP
C11: Existing OnPoint customers (Vietnam + Thailand) | E11: =400*(1+20%) -> 480 | F11: =ROUND(E11*(1+20%),0) -> 576 | G11: =ROUND(F11*(1+20%),0) -> 691 | H11: =ROUND(G11*(1+20%),0) -> 829 | J11: Baseline of 400 brands at end-2026, growing 20% per year on average. Scope: Vietnam + Thailand.
C12: Prospective customers selected for rollout in Vietnam | D12: brands | E12: 60 | F12: =ROUND(F11*'08 Scenarios'!F9,0) -> 288 | G12: =ROUND(G11*'08 Scenarios'!G9,0) -> 484 | H12: =ROUND(H11*'08 Scenarios'!H9,0) -> 663 | J12: Target of 60 brands in year one, with the take-up rate increasing in later years
C13: Non-OnPoint brands and distributors in Vietnam | D13: brands | E13: ='03 Strategy'!E10 -> 0 | F13: ='03 Strategy'!F10 -> 79 | G13: ='03 Strategy'!G10 -> 119 | H13: ='03 Strategy'!H10 -> 158 | J13: Calculated as total working days in the year ÷ average days to close one brand × number of sales FTEs
C14: Thailand brands via CREA | D14: brands | E14: ='08 Scenarios'!E15 -> 0 | F14: ='08 Scenarios'!F15 -> 0 | G14: ='08 Scenarios'!G15 -> 30 | H14: ='08 Scenarios'!H15 -> 50 | J14: When acquired at end-2024, CREA held a portfolio of 84+ international brands (250 brands in total after the merger => CREA brands ≈ 34%)
C15: Total active brands at year-end | D15: brands | E15: =SUM(E12:E14) -> 60 | F15: =SUM(F12:F14) -> 367 | G15: =SUM(G12:G14) -> 633 | H15: =SUM(H12:H14) -> 871 | J15: Total brands expected to join from Vietnam, external partners and CREA.
C16: Brand-years used for net recovery | D16: brand-years | E16: =E15 -> 60 | F16: =(E15+F15)/2*F8/12 -> 213.5 | G16: =(F15+G15)/2*G8/12 -> 500 | H16: =(G15+H15)/2*H8/12 -> 752 | J16: 2027 uses year-end brand count directly, not multiplied by 6/12. From 2028: average of opening/closing brands × selling months / 12.
C18: 03 NET RECOVERY PER BRAND (most critical assumption to validate in P0)
C19: Share of large brands (Group A) | D19: % | E19: ='08 Scenarios'!E21 -> 0.2 | F19: ='08 Scenarios'!F21 -> 0.2 | G19: ='08 Scenarios'!G21 -> 0.2 | H19: ='08 Scenarios'!H21 -> 0.2 | J19: Group A share per the active scenario on 08 Scenarios.
C20: Steady-state net recovery, Group A / brand-year | D20: USD | E20: 1500000 | F20: 1500000 | G20: 1500000 | H20: 1500000 | J20: Group A benchmark of USD 1.5 million/brand-year: assumes company revenue of VND 3,000 billion × 1.25% return rate ≈ VND 37.5 billion, roughly USD 1.5 million. This is a reference returns volume that must be checked at brand level and validated in P0; VNR500 does not confirm these two parameters.
C21: Steady-state net recovery, Group B / brand-year | D21: USD | E21: 160000 | F21: 160000 | G21: 160000 | H21: 160000 | J21: Group B benchmark of USD 160,000/brand-year: assumes revenue of VND 40 billion × 60% COGS ÷ 6 inventory turns = average inventory of VND 4 billion, about USD 160,000 at VND 25,000/USD. This is average inventory, not annual liquidation flow; SeABank data only supports the SME classification.
C22: Share of net recovery handed over by brands | D22: % | E22: 0.3 | F22: 0.5 | G22: 0.5 | H22: 0.5 | J22: Reflects the share of inventory brands hand over (not all of it, as brands keep some inventory on their balance sheet)
C23: Share of net recovery that is still liquidatable | E23: 0.7 | F23: 0.7 | G23: 0.7 | H23: 0.7 | J23: Assumes only 70% of total inventory/returns value is eligible for resale
C24: Average net recovery / brand-year | D24: USD | E24: =(E19*E20+(1-E19)*E21)*E22*E23 -> 89880 | F24: =(F19*F20+(1-F19)*F21)*F22*F23 -> 149800 | G24: =(G19*G20+(1-G19)*G21)*G22*G23 -> 149800 | H24: =(H19*H20+(1-H19)*H21)*H22*H23 -> 149800 | J24: Group A/B weighted average × handover rate × liquidatable rate.
C26: 04 CHANNEL MIX, UPLIFT OVER BASELINE AND CHANNEL COSTS
C27: B2B share of net recovery | D27: % | E27: ='08 Scenarios'!E33 -> 0.6 | F27: ='08 Scenarios'!F33 -> 0.6 | G27: ='08 Scenarios'!G33 -> 0.6 | H27: ='08 Scenarios'!H33 -> 0.6 | J27: B2B mix taken from 08 Scenarios; each driver has its own scenario selection.
C28: B2B uplift over brand baseline (liquidation quote) | D28: % | E28: ='08 Scenarios'!E39 -> 0.35 | F28: ='08 Scenarios'!F39 -> 0.35 | G28: ='08 Scenarios'!G39 -> 0.35 | H28: ='08 Scenarios'!H39 -> 0.35 | J28: B2B uplift per the active scenario on 08 Scenarios.
C29: B2C uplift over brand baseline | D29: % | E29: ='08 Scenarios'!E45 -> 0.75 | F29: ='08 Scenarios'!F45 -> 0.75 | G29: ='08 Scenarios'!G45 -> 0.75 | H29: ='08 Scenarios'!H45 -> 0.75 | J29: B2C uplift per the active scenario on 08 Scenarios.
C30: B2C channel fees borne by brand / buyer-paid price | D30: % | E30: 0.1 | F30: 0.1 | G30: 0.1 | H30: 0.1 | J30: 10% of B2C sales after returns: marketplace fees (4–6.05% commission + 6% transaction fee per MISA eShop 2026, to be checked against Seller Center) plus part of shipping. Borne by the brand; ValueBridge advances and deducts at settlement; not ValueBridge revenue/cost.
C31: B2B logistics fees borne by brand / buyer-paid price | D31: % | E31: 0.05 | F31: 0.05 | G31: 0.05 | H31: 0.05 | J31: ValueBridge advances payment to the logistics provider and recovers it from the brand by deduction at settlement. Calculated on the buyer price for B2B lots; not a buyer surcharge nor ValueBridge revenue/cost under the agency assumption.
C32: B2C returns / sales before returns | D32: % | E32: ='08 Scenarios'!E51 -> 0.18 | F32: ='08 Scenarios'!F51 -> 0.18 | G32: ='08 Scenarios'!G51 -> 0.18 | H32: ='08 Scenarios'!H51 -> 0.18 | J32: Return rate taken from 08 Scenarios.

Sheet 02 Fee Schedule
C2: ValueBridge | Gain-Share Fee Schedule
C3: All ValueBridge income is fees (agency model) and is recognised as net revenue. Gross transaction value, payments to brands and pass-through channel costs are NOT revenue.
C5: Line item | D5: Unit | E5: 2027 | F5: 2028 | G5: 2029 | H5: 2030 | J5: Notes
C7: 01 GAIN-SHARE SUCCESS FEE (both channels, on net recovery)
C8: Base fee on net recovery up to baseline | D8: % | E8: 0.1 | F8: 0.1 | G8: 0.1 | H8: 0.1 | J8: Same rate for B2B and B2C (channel-neutral). Close to B-Stock's reference fee of about 7.5% (Forbes estimate, cited via Consumer Goodies).
C9: Share of net recovery above baseline | D9: % | E9: 0.25 | F9: 0.25 | G9: 0.25 | H9: 0.25 | J9: ValueBridge earns extra only when recovery beats the brand's own disposal option.
C10: Cap on total success fee / net recovery | D10: % | E10: 0.25 | F10: 0.25 | G10: 0.25 | H10: 0.25 | J10: Protective cap. The commitment that brand net proceeds ≥ baseline is tested on sheet 09 Checks.
C11: Intake fee per lot (credited against success fee) | D11: USD | E11: 300 | F11: 300 | G11: 300 | H11: 300 | J11: Memo only: credited when the lot sells, so it is not additional revenue in the base case. Waived for Programme members.
C14: 02 VALUEBRIDGE PROGRAM SUBSCRIPTION FEE
C15: Program fee per brand per month | D15: USD | E15: 1000 | F15: 1250 | G15: 1250 | H15: 1250 | J15: Inventory risk dashboard (Opollo data), monthly review, priority in joint livestreams, lot intake support and reporting on volume diverted from destruction.
C16: Share of active brands subscribing to the program | D16: % | E16: 0.15 | F16: 0.4 | G16: 0.5 | H16: 0.5 | J16: Offered after a brand's second lot. 2027 uses a minimal manually-run version from H2; first dashboard version launches mid-2028.
C18: 03 VALUE-ADDED SERVICES (separately agreed)
C19: Value-added services revenue / net recovery | D19: % | E19: 0.025 | F19: 0.025 | G19: 0.025 | H19: 0.025 | J19: Repackaging/bundling, relabelling, dedicated campaigns and storage beyond 60 days. This line counts fee revenue; the model does not yet separate delivery costs.
C22: 04 BUYER FEES (B2B)
C23: Verified member buyers (converted to billing periods) | D23: buyers | E23: 10 | F23: 80 | G23: 200 | H23: 400 | J23: Free pilot phase generates no revenue. The model assumes 10 paying buyers in H2 2027: 10 × USD 1,500/year × 6/12 = USD 7,500.
C24: Annual buyer membership fee | D24: USD | E24: 1500 | F24: 1500 | G24: 1500 | H24: 1500 | J24: Early access to graded lots with complete data packs.
C25: Buyer surcharge on B2B lot value sold | D25: % | E25: 0.02 | F25: 0.02 | G25: 0.02 | H25: 0.02 | J25: Buyer surcharge 2% × (B2B baseline + B2B uplift). Not charged on the 5% B2B logistics fee borne by the brand, which ValueBridge advances and deducts at settlement. The 2% rate must be validated in the pilot.

Sheet 03 Strategy
C2: ValueBridge | Resources, Costs & Collection Terms
C3: Fixed cost data carried over from the original model (03 Strategy), except items marked as new
C5: Line item | D5: Unit | E5: 2027 | F5: 2028 | G5: 2029 | H5: 2030 | J5: Notes
C7: 01 SALES CAPACITY & COMMISSION — from original model
C8: Working days / full-year sales FTE (excl. public holidays) | D8: Days | E8: 237 | F8: 237 | G8: 237 | H8: 237 | J8: 8 hours a day, 5 days a week for 12 months, excluding public holidays
C9: Sales days / brand successfully closed | D9: Days | E9: 30 | F9: 30 | G9: 30 | H9: 30
C10: Non-OnPoint brands closed in Vietnam | D10: Brands | E10: =ROUND(E8/E9*E14,0) -> 0 | F10: =ROUND(F8/F9*F14,0) -> 79 | G10: =ROUND(G8/G9*G14,0) -> 119 | H10: =ROUND(H8/H9*H14,0) -> 158
C11: Total commission / brands closed | D11: USD | E11: =E10*E21 -> 0 | F11: =F10*F21 -> 19750 | G11: =G10*G21 -> 29750 | H11: =H10*H21 -> 39500 | J11: Brands closed = 237 working days/year ÷ 30 days/brand × sales FTEs; × USD 250/brand for total commission.
C12: 01 FULL-TIME HEADCOUNT — from original model | J12: Staff and fixed costs are charged for a full 12 months, including 2027; 2027 revenue covers only 6 selling months per 01 Market.
C13: Additional inspection & reconciliation staff (reverse logistics) | D13: FTEs | E13: 4 | F13: 8 | G13: 16 | H13: 20 | J13: Hired to inspect returns and reconcile. 2027: 4 for Vietnam brands; 2028: 8 for Vietnam and non-OnPoint SMEs; 2029: 10 in Vietnam and 6 covering Thailand; 2030: 12 in Vietnam and 8 covering Thailand.
C14: Sales staff closing non-OnPoint brands | D14: FTEs | E14: ='08 Scenarios'!E27 -> 0 | F14: ='08 Scenarios'!F27 -> 10 | G14: ='08 Scenarios'!G27 -> 15 | H14: ='08 Scenarios'!H27 -> 20 | J14: Non-OnPoint brand sales headcount taken from 08 Scenarios.
C15: B2B operations staff | D15: FTEs | E15: =ROUND('01 Market'!E27*'01 Market'!E16/5,0) -> 7 | F15: =ROUND('01 Market'!F27*'01 Market'!F16/5,0) -> 26 | G15: =ROUND('01 Market'!G27*'01 Market'!G16/5,0) -> 60 | H15: =ROUND('01 Market'!H27*'01 Market'!H16/5,0) -> 90 | J15: B2B headcount: about 5 brands per person in 2027–2030
C16: B2C operations & livestream staff | D16: FTEs | E16: 8 | F16: 8 | G16: 12 | H16: 12 | J16: 2027–2028: 4 rotating livestreamers, 2 page/KOL managers, 2 editors. 2029–2030: plus 2 livestreamers, 1 page/KOL manager and 1 editor for Thai content produced in Vietnam.
C17: Outsourced KOCs/hosts per Mega Sale event (4 hours each) | D17: people/event | E17: 2 | F17: 2 | G17: 3 | H17: 3 | J17: KOCs work per session, not salaried FTEs. Planned 2–3 per event in 2027–2030
C18: 02 FULLY-LOADED COST PER FTE (USD/year) — from original model | J18: Annual staff cost assumes 13 months of salary.
C19: Inspection & reconciliation staff (reverse logistics) / person | D19: USD | E19: 13000 | F19: 13000 | G19: 13000 | H19: 13000 | J19: USD 1,000/month × 13 months = USD 13,000/person-year; about VND 25 million/month, blended lead and staff level.
C20: Sales staff / person | D20: USD | E20: 10010 | F20: 10010 | G20: 10010 | H20: 10010 | J20: USD 770/month × 13 months = USD 10,010/person-year; about VND 20 million/month, blended lead and staff level.
C21: Sales commission / brand | D21: USD | E21: 250 | F21: 250 | G21: 250 | H21: 250 | J21: Fixed commission of USD 250 per brand signed; cost is based on brands closed, not on months or sales volume.
C22: B2B staff / person | D22: USD | E22: 10010 | F22: 10010 | G22: 10010 | H22: 10010 | J22: USD 770/month × 13 months = USD 10,010/person-year; about VND 20 million/month, blended lead and staff level.
C23: Average cost / B2C staff | D23: USD | E23: 10010 | F23: 10010 | G23: 10010 | H23: 10010 | J23: USD 770/month × 13 months = USD 10,010/person-year; about VND 20 million/month, blended lead and staff level.
C24: Fixed booking fee / KOC / 4-hour Mega Sale session | D24: USD/session | E24: 200 | F24: 200 | G24: 200 | H24: 200 | J24: Planning assumption: VND 1 million/hour × 4 hours × 1.25 peak factor = VND 5 million; ÷ VND 25,000/USD = USD 200/session. Nguoi Lao Dong reports KOCs at ~VND 1 million/hour and peak-season bookings of VND 3–10 million/session: https://nld.com.vn/dich-vu-livestream-ban-hang-tet-kin-lich-gia-thue-kol-tang-chong-mat-196260118121654386.htm. Cast fee only; affiliate commission excluded until attributed sales and the paying party are confirmed. TikTok: https://seller-vn.tiktok.com/university/essay?knowledge_id=775581994239745&lang=en
C25: 03 OTHER FIXED COSTS & CAPEX
C26: Systems & data / year | D26: USD | E26: 17000 | F26: 17000 | G26: 17000 | H26: 17000 | J26: Only the incremental Opollo enhancement and maintenance for ValueBridge: 0.6 developer FTE × USD 1,350 × 12 = USD 9,720; 0.2 QA FTE × USD 1,180 × 12 = USD 2,832; infrastructure USD 350 × 12 = USD 4,200. Total USD 16,752, rounded to USD 17,000/year. Salary reference: https://topdev.vn/download-report/
C27: Sales travel / person / year | D27: USD | E27: =10*E8 -> 2370 | F27: =10*F8 -> 2370 | G27: =10*G8 -> 2370 | H27: =10*H8 -> 2370 | J27: Round-trip taxi est. VND 250,000/day ≈ USD 10/day. A sales FTE works 237 days/year, so the unit cost is USD 2,370/person-year; team cost = this unit cost × sales FTEs on sheet 05.
C28: Legal & compliance / year | D28: USD | E28: 6900 | F28: 6900 | G28: 6900 | H28: 6900 | J28: Ongoing legal counsel for the whole program: VND 15 million/month × 12 = VND 180 million/year, approx. USD 6,900/year at about VND 26,000/USD. (https://phonggialawfirm.com/dich-vu-luat-su-tu-van-doanh-nghiep/)
C29: Buyers & partners / year | D29: USD | E29: =1545+3*'02 Fee Schedule'!E23 -> 1575 | F29: =1545+3*'02 Fee Schedule'!F23 -> 1785 | G29: =1545+3*'02 Fee Schedule'!G23 -> 2145 | H29: =1545+3*'02 Fee Schedule'!H23 -> 2745 | J29: Assumes 4 buyer networking sessions/year × 4 hours/session × VND 2.5 million/hour ≈ USD 1,545/year, plus USD 3 per verified buyer. Event cost is a single annual amount, not multiplied by brand count. References: https://circo.co/services and https://thekyb.com/pricing/
C30: Capital expenditure in the year | D30: USD | E30: =E31+E32+E33 -> 12400 | F30: =F31+F32+F33 -> 19950 | G30: =G31+G32+G33 -> 30675 | H30: =H31+H32+H33 -> 23475 | J30: Capex driven by headcount additions: laptops USD 600 each (~VND 15 million), desk phones USD 15 each (~VND 0.4 million) for new sales staff; a USD 1,000 camera bought once in 2027. Total capex = the three lines below.
C31: Laptop | D31: USD | E31: =(E13+E14+E15+E16)*600 -> 11400 | F31: =((F13+F14+F15+F16)-(E13+E14+E15+E16))*600 -> 19800 | G31: =((G13+G14+G15+G16)-(F13+F14+F15+F16))*600 -> 30600 | H31: =((H13+H14+H15+H16)-(G13+G14+G15+G16))*600 -> 23400
C32: Telephone | D32: USD | E32: =E14*15 -> 0 | F32: =(F14-E14)*15 -> 150 | G32: =(G14-F14)*15 -> 75 | H32: =(H14-G14)*15 -> 75
C33: Camera | D33: USD | E33: 1000 | J33: Camera purchased in the first year only (2027).
C34: Depreciation period | D34: year | E34: 3 | F34: 3 | G34: 3 | H34: 3 | J34: 3-year straight-line depreciation for laptops, phones and the camera.
C35: Corporate income tax rate | D35: % | E35: 0.2 | F35: 0.2 | G35: 0.2 | H35: 0.2 | J35: Tax rate kept from the original model. Provisional tax formula and loss carry-forward are on 05 P&L row 42.
C36: 05 COLLECTION TERMS
C37: B2B fee collection days | D37: days | E37: 30 | F37: 30 | G37: 45 | H37: 45 | J37: Fees are deducted at settlement after the buyer pays; uses the B2B receivable days from the original model.
C38: B2C fee collection days | D38: days | E38: 7 | F38: 7 | G38: 7 | H38: 7 | J38: Platform payout period (per original model).
C39: Subscription & value-added services collection days | D39: days | E39: 30 | F39: 30 | G39: 30 | H39: 30 | J39: Invoiced monthly.
C40: Days from collection to remittance to brands | D40: days | E40: 15 | F40: 15 | G40: 15 | H40: 15 | J40: Settlement and remittance cycle to brands after the buyer/marketplace pays. Assumed 15 days; to be fixed in the mandate. Used only for the memo line on sheet 06; does not affect FCF.
C41: 06 B2C RETURNS HANDLING COSTS (borne by ValueBridge; goods value borne by brands)
C42: Average B2C order value (AOV) | D42: USD | E42: 12 | F42: 12 | G42: 12 | H42: 12 | J42: Assumes about VND 300,000/order (clearance bundles) ÷ VND 25,000/USD. Used to convert returns value into number of returned orders. To be validated in the pilot.
C43: Return shipping / returned order | D43: USD | E43: 1 | F43: 1 | G43: 1 | H43: 1 | J43: Assumes about VND 25,000/order for return shipping charged by the marketplace/carrier. Paid by ValueBridge, not recovered from brands. To be checked against marketplace/carrier rate cards.
C44: Receiving, inspection, repackaging & return-to-brand cost / returned order | D44: USD | E44: 0.4 | F44: 0.4 | G44: 0.4 | H44: 0.4 | J44: Assumes about VND 10,000/order (inspection labour, packing materials, consolidated return to brand). Borne by ValueBridge.

Sheet 04 Operations
C2: ValueBridge | Volume & Settlement Waterfall
C3: Brand-years → net recovery → baseline and uplift → buyer payments → remittance to brands. Row 31 is the ValueBridge success fee; goods proceeds and channel fees are not ValueBridge revenue.
C5: Line item | D5: Unit | E5: 2027 | F5: 2028 | G5: 2029 | H5: 2030 | J5: Notes
C8: 01 NET RECOVERY
C9: Brand-years | D9: brand-years | E9: ='01 Market'!E16 -> 60 | F9: ='01 Market'!F16 -> 213.5 | G9: ='01 Market'!G16 -> 500 | H9: ='01 Market'!H16 -> 752
C10: Net recovery (after channel costs) | D10: USD | E10: =E9*'01 Market'!E24 -> 5392800 | F10: =F9*'01 Market'!F24 -> 31982300 | G10: =G9*'01 Market'!G24 -> 74900000 | H10: =H9*'01 Market'!H24 -> 112649600
C11: B2B net recovery | D11: USD | E11: =E10*'01 Market'!E27 -> 3235680 | F11: =F10*'01 Market'!F27 -> 19189380 | G11: =G10*'01 Market'!G27 -> 44940000 | H11: =H10*'01 Market'!H27 -> 67589760
C12: B2C net recovery | D12: USD | E12: =E10-E11 -> 2157120 | F12: =F10-F11 -> 12792920 | G12: =G10-G11 -> 29960000 | H12: =H10-H11 -> 45059840
C14: 02 BASELINE AND UPLIFT
C15: B2B baseline (brand's own disposal option) | D15: USD | E15: =E11/(1+'01 Market'!E28) -> 2396800 | F15: =F11/(1+'01 Market'!F28) -> 14214356 | G15: =G11/(1+'01 Market'!G28) -> 33288889 | H15: =H11/(1+'01 Market'!H28) -> 50066489
C16: B2B uplift above baseline | D16: USD | E16: =E11-E15 -> 838880 | F16: =F11-F15 -> 4975024.4 | G16: =G11-G15 -> 11651111 | H16: =H11-H15 -> 17523271
C17: B2C baseline | D17: USD | E17: =E12/(1+'01 Market'!E29) -> 1232640 | F17: =F12/(1+'01 Market'!F29) -> 7310240 | G17: =G12/(1+'01 Market'!G29) -> 17120000 | H17: =H12/(1+'01 Market'!H29) -> 25748480
C18: B2C uplift above baseline | D18: USD | E18: =E12-E17 -> 924480 | F18: =F12-F17 -> 5482680 | G18: =G12-G17 -> 12840000 | H18: =H12-H17 -> 19311360
C20: 03 BUYER SALES AND BRAND SETTLEMENT
C21: Required B2B lot price paid by buyers (excl. 2% buyer fee) | D21: USD | E21: =E11/(1-'01 Market'!E31) -> 3405978.9 | F21: =F11/(1-'01 Market'!F31) -> 20199347 | G21: =G11/(1-'01 Market'!G31) -> 47305263 | H21: =H11/(1-'01 Market'!H31) -> 71147116 | J21: Required buyer price is back-solved from the B2B net recovery target. Logistics fees are not charged separately to buyers; they are deducted from the brand's sales proceeds. This is not an independent forecast of winning lot prices.
C22: Required B2C buyer sales after returns | D22: USD | E22: =E12/(1-'01 Market'!E30) -> 2396800 | F22: =F12/(1-'01 Market'!F30) -> 14214356 | G22: =G12/(1-'01 Market'!G30) -> 33288889 | H22: =H12/(1-'01 Market'!H30) -> 50066489 | J22: Required buyer sales are back-solved from the B2C net recovery target. Channel fees are borne by the brand and deducted at settlement; this is not an independent selling-price forecast.
C23: B2C sales before returns | D23: USD | E23: =E22/(1-'01 Market'!E32) -> 2922926.8 | F23: =F22/(1-'01 Market'!F32) -> 17334580 | G23: =G22/(1-'01 Market'!G32) -> 40596206 | H23: =H22/(1-'01 Market'!H32) -> 61056694
C24: Value of returned B2C lots | D24: USD | E24: =E23-E22 -> 526126.83 | F24: =F23-F22 -> 3120224.4 | G24: =G23-G22 -> 7307317.1 | H24: =H23-H22 -> 10990205 | J24: B2C sales before returns minus sales after returns. Returned goods come back and are handed back to the brand (row 33); buyer refunds are already netted in sales after returns.
C25: Total channel/logistics fees borne by brands, advanced by ValueBridge | D25: USD | E25: =(E21-E11)+(E22-E12) -> 409978.95 | F25: =(F21-F11)+(F22-F12) -> 2431402.9 | G25: =(G21-G11)+(G22-G12) -> 5694152 | H25: =(H21-H11)+(H22-H12) -> 8564004.7 | J25: ValueBridge advances channel/logistics fees and recovers them from brands at settlement. The outflows and recoveries sit on 06 Cash Flow; these items are excluded from the ValueBridge P&L under the agency assumption.
C26: of which: B2B logistics fees borne by brands | D26: USD | E26: =E21-E11 -> 170298.95 | F26: =F21-F11 -> 1009967.4 | G26: =G21-G11 -> 2365263.2 | H26: =H21-H11 -> 3557355.8 | J26: 5% × buyer price for B2B lots; ValueBridge advances and recovers by deduction at settlement.
C27: of which: B2C channel fees borne by brands | D27: USD | E27: =E22-E12 -> 239680 | F27: =F22-F12 -> 1421435.6 | G27: =G22-G12 -> 3328888.9 | H27: =H22-H12 -> 5006648.9 | J27: 3% × B2C buyer sales after returns; ValueBridge advances and recovers by deduction at settlement.
C28: Recovery after returns and channel/logistics fees | D28: USD | E28: =E21+E23-E24-E25 -> 5392800 | F28: =F21+F23-F24-F25 -> 31982300 | G28: =G21+G23-G24-G25 -> 74900000 | H28: =H21+H23-H24-H25 -> 112649600 | J28: B2B sales + B2C sales before returns − returned lot value − channel/logistics fees; ties to the net recovery target in row 12.
C29: ValueBridge success fee deducted at settlement | D29: USD | E29: ='05 P&L'!E11 -> 803784 | F29: ='05 P&L'!F11 -> 4766885.7 | G29: ='05 P&L'!G11 -> 11163667 | H29: ='05 P&L'!H11 -> 16790155 | J29: Success fee from the P&L; this is ValueBridge revenue, distinct from the two third-party fees.
C30: Cash paid to brands from successfully sold lots | D30: USD | E30: =E28-E29 -> 4589016 | F30: =F28-F29 -> 27215414 | G30: =G28-G29 -> 63736333 | H30: =H28-H29 -> 95859445 | J30: Payments to brands from successfully sold lots, after channel fees and the ValueBridge success fee. Returned B2C lot value is tracked separately in row 26.
C31: B2C returns handed back to brands (in goods, not cash) | D31: USD | E31: =E24 -> 526126.83 | F31: =F24 -> 3120224.4 | G31: =G24 -> 7307317.1 | H31: =H24 -> 10990205 | J31: Returned B2C lot value in row 26 is handed back to brands as goods; not a ValueBridge cash outflow.
C32: Total value returned to brands (cash + returned goods) | D32: USD | E32: =E30+E31 -> 5115142.8 | F32: =F30+F31 -> 30335639 | G32: =G30+G31 -> 71043650 | H32: =H30+H31 -> 1.0684965e+08 | J32: Row 32 (cash) plus row 33 (returned goods).
C34: 04 MEGA SALE LIVESTREAM — OUTSOURCED KOCs | J34: Booking/cast fee, excluding affiliate commission
C35: Mega Sale events per year | D35: events | E35: 14 | F35: 25 | G35: 25 | H35: 25 | J35: Planned calendar of 14 sessions in 2027 and 25 sessions per year in 2028–2030, based on double-date sales, pay days and selected seasonal occasions. Overlapping dates are not counted as separate sessions.
C36: KOCs/hosts hired per event | D36: people/event | E36: ='03 Strategy'!E17 -> 2 | F36: ='03 Strategy'!F17 -> 2 | G36: ='03 Strategy'!G17 -> 3 | H36: ='03 Strategy'!H17 -> 3 | J36: Linked to 03 Strategy row 20; session-based contributors, not included in B2C staff payroll.
C37: Cast fee per KOC per 4-hour session | D37: USD/session | E37: ='03 Strategy'!E24 -> 200 | F37: ='03 Strategy'!F24 -> 200 | G37: ='03 Strategy'!G24 -> 200 | H37: ='03 Strategy'!H24 -> 200 | J37: Linked to 03 Strategy row 27; VND 5 million ≈ USD 200 at the planning rate of VND 25,000/USD. https://nld.com.vn/dich-vu-livestream-ban-hang-tet-kin-lich-gia-thue-kol-tang-chong-mat-196260118121654386.htm
C38: Total Mega Sale KOC booking cost / year | D38: USD | E38: =PRODUCT(E35:E37) -> 5600 | F38: =PRODUCT(F35:F37) -> 10000 | G38: =PRODUCT(G35:G37) -> 15000 | H38: =PRODUCT(H35:H37) -> 15000 | J38: Events × KOCs per event × cast fee/session. No affiliate commission in the base case until creator-attributed sales exist.
C40: 05 B2C RETURNS HANDLING COSTS (borne by ValueBridge) | J40: Returned goods value is borne by brands (handed back as goods, row 33). ValueBridge bears only return shipping and handling costs.
C41: Returned B2C orders | D41: orders | E41: =IF('03 Strategy'!E42=0,0,E24/'03 Strategy'!E42) -> 43843.902 | F41: =IF('03 Strategy'!F42=0,0,F24/'03 Strategy'!F42) -> 260018.7 | G41: =IF('03 Strategy'!G42=0,0,G24/'03 Strategy'!G42) -> 608943.09 | H41: =IF('03 Strategy'!H42=0,0,H24/'03 Strategy'!H42) -> 915850.41 | J41: Returned B2C lot value (row 26) ÷ AOV on 03 Strategy row 44.
C42: Handling cost / returned order | D42: USD/order | E42: ='03 Strategy'!E43+'03 Strategy'!E44 -> 1.4 | F42: ='03 Strategy'!F43+'03 Strategy'!F44 -> 1.4 | G42: ='03 Strategy'!G43+'03 Strategy'!G44 -> 1.4 | H42: ='03 Strategy'!H43+'03 Strategy'!H44 -> 1.4 | J42: Return shipping + receiving, inspection, packing and return to brand (03 Strategy rows 45–46).
C43: Total returns handling cost (borne by ValueBridge) | D43: USD | E43: =E41*E42 -> 61381.463 | F43: =F41*F42 -> 364026.18 | G43: =G41*G42 -> 852520.33 | H43: =H41*H42 -> 1282190.6 | J43: Flows into 05 P&L row 24 as a direct cost.

Sheet 05 P&L
C2: ValueBridge | Profit & Loss
C3: Revenue includes fees only. Payments to brands and pass-through channel costs are not recognised.
C5: Line item | D5: Unit | E5: 2027 | F5: 2028 | G5: 2029 | H5: 2030 | J5: Notes
C7: 01 NET REVENUE
C8: B2B success fee (before cap) | D8: USD | E8: =('02 Fee Schedule'!E8*'04 Operations'!E15+'02 Fee Schedule'!E9*'04 Operations'!E16) -> 449400 | F8: =('02 Fee Schedule'!F8*'04 Operations'!F15+'02 Fee Schedule'!F9*'04 Operations'!F16) -> 2665191.7 | G8: =('02 Fee Schedule'!G8*'04 Operations'!G15+'02 Fee Schedule'!G9*'04 Operations'!G16) -> 6241666.7 | H8: =('02 Fee Schedule'!H8*'04 Operations'!H15+'02 Fee Schedule'!H9*'04 Operations'!H16) -> 9387466.7
C9: B2C success fee (before cap) | D9: USD | E9: =('02 Fee Schedule'!E8*'04 Operations'!E17+'02 Fee Schedule'!E9*'04 Operations'!E18) -> 354384 | F9: =('02 Fee Schedule'!F8*'04 Operations'!F17+'02 Fee Schedule'!F9*'04 Operations'!F18) -> 2101694 | G9: =('02 Fee Schedule'!G8*'04 Operations'!G17+'02 Fee Schedule'!G9*'04 Operations'!G18) -> 4922000 | H9: =('02 Fee Schedule'!H8*'04 Operations'!H17+'02 Fee Schedule'!H9*'04 Operations'!H18) -> 7402688
C10: Adjustment for fees above cap | D10: USD | E10: =-MAX(0,E8-'02 Fee Schedule'!E10*'04 Operations'!E11)-MAX(0,E9-'02 Fee Schedule'!E10*'04 Operations'!E12) -> 0 | F10: =-MAX(0,F8-'02 Fee Schedule'!F10*'04 Operations'!F11)-MAX(0,F9-'02 Fee Schedule'!F10*'04 Operations'!F12) -> 0 | G10: =-MAX(0,G8-'02 Fee Schedule'!G10*'04 Operations'!G11)-MAX(0,G9-'02 Fee Schedule'!G10*'04 Operations'!G12) -> 0 | H10: =-MAX(0,H8-'02 Fee Schedule'!H10*'04 Operations'!H11)-MAX(0,H9-'02 Fee Schedule'!H10*'04 Operations'!H12) -> 0
C11: 1. Gain-share success fee | D11: USD | E11: =SUM(E8:E10) -> 803784 | F11: =SUM(F8:F10) -> 4766885.7 | G11: =SUM(G8:G10) -> 11163667 | H11: =SUM(H8:H10) -> 16790155
C12: 2. Program subscription fee | D12: USD | E12: =(0+'01 Market'!E15)/2*'02 Fee Schedule'!E16*'02 Fee Schedule'!E15*'01 Market'!E8 -> 27000 | F12: =('01 Market'!E15+'01 Market'!F15)/2*'02 Fee Schedule'!F16*'02 Fee Schedule'!F15*'01 Market'!F8 -> 1281000 | G12: =('01 Market'!F15+'01 Market'!G15)/2*'02 Fee Schedule'!G16*'02 Fee Schedule'!G15*'01 Market'!G8 -> 3750000 | H12: =('01 Market'!G15+'01 Market'!H15)/2*'02 Fee Schedule'!H16*'02 Fee Schedule'!H15*'01 Market'!H8 -> 5640000 | J12: Average brands × subscription rate × monthly fee × selling months.
C13: 3. Value-added services | D13: USD | E13: ='04 Operations'!E10*'02 Fee Schedule'!E19 -> 134820 | F13: ='04 Operations'!F10*'02 Fee Schedule'!F19 -> 799557.5 | G13: ='04 Operations'!G10*'02 Fee Schedule'!G19 -> 1872500 | H13: ='04 Operations'!H10*'02 Fee Schedule'!H19 -> 2816240 | J13: Service revenue equals 2.5% of net recovery. The model does not yet separate direct delivery costs for these services.
C14: Buyer membership fees | D14: USD | E14: ='02 Fee Schedule'!E23*'02 Fee Schedule'!E24*'01 Market'!E8/12 -> 7500 | F14: ='02 Fee Schedule'!F23*'02 Fee Schedule'!F24*'01 Market'!F8/12 -> 120000 | G14: ='02 Fee Schedule'!G23*'02 Fee Schedule'!G24*'01 Market'!G8/12 -> 300000 | H14: ='02 Fee Schedule'!H23*'02 Fee Schedule'!H24*'01 Market'!H8/12 -> 600000
C15: Buyer surcharge on B2B lot value | D15: USD | E15: =('04 Operations'!E15+'04 Operations'!E16)*'02 Fee Schedule'!E25 -> 64713.6 | F15: =('04 Operations'!F15+'04 Operations'!F16)*'02 Fee Schedule'!F25 -> 383787.6 | G15: =('04 Operations'!G15+'04 Operations'!G16)*'02 Fee Schedule'!G25 -> 898800 | H15: =('04 Operations'!H15+'04 Operations'!H16)*'02 Fee Schedule'!H25 -> 1351795.2 | J15: B2B lot value sold = B2B baseline + B2B uplift on 04 Operations. The 2% fee applies to this value, not to the 5% logistics fee.
C16: 4. Buyer fees | D16: USD | E16: =E14+E15 -> 72213.6 | F16: =F14+F15 -> 503787.6 | G16: =G14+G15 -> 1198800 | H16: =H14+H15 -> 1951795.2
C17: TOTAL NET REVENUE | D17: USD | E17: =E11+E12+E13+E16 -> 1037817.6 | F17: =F11+F12+F13+F16 -> 7351230.8 | G17: =G11+G12+G13+G16 -> 17984967 | H17: =H11+H12+H13+H16 -> 27198190
C18: Net revenue / net recovery | D18: % | E18: =IF('04 Operations'!E10=0,0,E17/'04 Operations'!E10) -> 0.19244504 | F18: =IF('04 Operations'!F10=0,0,F17/'04 Operations'!F10) -> 0.2298531 | G18: =IF('04 Operations'!G10=0,0,G17/'04 Operations'!G10) -> 0.24011972 | H18: =IF('04 Operations'!H10=0,0,H17/'04 Operations'!H10) -> 0.24144063
C19: Success fee / net recovery | D19: % | E19: =IF('04 Operations'!E10=0,0,E11/'04 Operations'!E10) -> 0.14904762 | F19: =IF('04 Operations'!F10=0,0,F11/'04 Operations'!F10) -> 0.14904762 | G19: =IF('04 Operations'!G10=0,0,G11/'04 Operations'!G10) -> 0.14904762 | H19: =IF('04 Operations'!H10=0,0,H11/'04 Operations'!H10) -> 0.14904762
C20: 03 DIRECT COSTS BORNE BY VALUEBRIDGE
C21: B2C returns handling cost | D21: USD | E21: =-'04 Operations'!E43 -> -61381.463 | F21: =-'04 Operations'!F43 -> -364026.18 | G21: =-'04 Operations'!G43 -> -852520.33 | H21: =-'04 Operations'!H43 -> -1282190.6 | J21: Return shipping and returns handling paid by ValueBridge, not recovered from brands. Returned goods value is borne by brands and therefore not recorded in the P&L.
C22: Profit after direct costs | D22: USD | E22: =E17+E21 -> 976436.14 | F22: =F17+F21 -> 6987204.6 | G22: =G17+G21 -> 17132446 | H22: =H17+H21 -> 25915999 | J22: Net revenue less direct costs.
C23: 04 FIXED COSTS
C24: Inspection & reconciliation staff | D24: USD | E24: =-'03 Strategy'!E13*'03 Strategy'!E19 -> -52000 | F24: =-'03 Strategy'!F13*'03 Strategy'!F19 -> -104000 | G24: =-'03 Strategy'!G13*'03 Strategy'!G19 -> -208000 | H24: =-'03 Strategy'!H13*'03 Strategy'!H19 -> -260000
C25: Sales staff | D25: USD | E25: =-'03 Strategy'!E14*'03 Strategy'!E20 -> 0 | F25: =-'03 Strategy'!F14*'03 Strategy'!F20 -> -100100 | G25: =-'03 Strategy'!G14*'03 Strategy'!G20 -> -150150 | H25: =-'03 Strategy'!H14*'03 Strategy'!H20 -> -200200
C26: B2B operations staff | D26: USD | E26: =-'03 Strategy'!E15*'03 Strategy'!E22 -> -70070 | F26: =-'03 Strategy'!F15*'03 Strategy'!F22 -> -260260 | G26: =-'03 Strategy'!G15*'03 Strategy'!G22 -> -600600 | H26: =-'03 Strategy'!H15*'03 Strategy'!H22 -> -900900
C27: B2C operations & livestream staff | D27: USD | E27: =-'03 Strategy'!E16*'03 Strategy'!E23 -> -80080 | F27: =-'03 Strategy'!F16*'03 Strategy'!F23 -> -80080 | G27: =-'03 Strategy'!G16*'03 Strategy'!G23 -> -120120 | H27: =-'03 Strategy'!H16*'03 Strategy'!H23 -> -120120
C28: Systems & data | D28: USD | E28: =-'03 Strategy'!E26 -> -17000 | F28: =-'03 Strategy'!F26 -> -17000 | G28: =-'03 Strategy'!G26 -> -17000 | H28: =-'03 Strategy'!H26 -> -17000
C29: Sales travel | D29: USD | E29: =-'03 Strategy'!E14*'03 Strategy'!E27 -> 0 | F29: =-'03 Strategy'!F14*'03 Strategy'!F27 -> -23700 | G29: =-'03 Strategy'!G14*'03 Strategy'!G27 -> -35550 | H29: =-'03 Strategy'!H14*'03 Strategy'!H27 -> -47400 | J29: Sales FTEs × round-trip taxi cost/person-year from 03 Strategy; headcount is not multiplied on both sheets.
C30: Legal & compliance | D30: USD | E30: =-'03 Strategy'!E28 -> -6900 | F30: =-'03 Strategy'!F28 -> -6900 | G30: =-'03 Strategy'!G28 -> -6900 | H30: =-'03 Strategy'!H28 -> -6900
C31: Buyers & partners | D31: USD | E31: =-'03 Strategy'!E29 -> -1575 | F31: =-'03 Strategy'!F29 -> -1785 | G31: =-'03 Strategy'!G29 -> -2145 | H31: =-'03 Strategy'!H29 -> -2745
C32: Sales commission on brands closed | D32: USD | E32: =-'03 Strategy'!E11 -> 0 | F32: =-'03 Strategy'!F11 -> -19750 | G32: =-'03 Strategy'!G11 -> -29750 | H32: =-'03 Strategy'!H11 -> -39500 | J32: Fixed commission of USD 250 per brand closed, from 03 Strategy row 13. Not based on liquidation sales.
C33: Mega Sale KOC booking fees | D33: USD | E33: =-'04 Operations'!E38 -> -5600 | F33: =-'04 Operations'!F38 -> -10000 | G33: =-'04 Operations'!G38 -> -15000 | H33: =-'04 Operations'!H38 -> -15000 | J33: Fixed per-session cost: Mega Sale events × KOCs/event × USD 200/session. KOCs are outsourced; not double-counted in B2C staff. Affiliate commission is excluded from the base case as there are no creator-attributed sales yet.
C34: Total fixed costs | D34: USD | E34: =SUM(E24:E33) -> -233225 | F34: =SUM(F24:F33) -> -623575 | G34: =SUM(G24:G33) -> -1185215 | H34: =SUM(H24:H33) -> -1609765
C35: EBITDA | D35: USD | E35: =E22+E34 -> 743211.14 | F35: =F22+F34 -> 6363629.6 | G35: =G22+G34 -> 15947231 | H35: =H22+H34 -> 24306234 | J35: Profit after direct costs (row 25) less total fixed costs (row 37).
C36: EBITDA margin (excl. VAS direct costs) | D36: % | E36: =IF(E17=0,0,E35/E17) -> 0.71612886 | F36: =IF(F17=0,0,F35/F17) -> 0.86565499 | G36: =IF(G17=0,0,G35/G17) -> 0.88669785 | H36: =IF(H17=0,0,H35/H17) -> 0.89367103
C38: 05 DEPRECIATION, TAX & PROFIT
C39: Depreciation | D39: USD | E39: =-(IF(2027-2027<'03 Strategy'!E34,'03 Strategy'!E30/'03 Strategy'!E34,0)) -> -4133.3333 | F39: =-(IF(2028-2027<'03 Strategy'!E34,'03 Strategy'!E30/'03 Strategy'!E34,0)+IF(2028-2028<'03 Strategy'!F34,'03 Strategy'!F30/'03 Strategy'!F34,0)) -> -10783.333 | G39: =-(IF(2029-2027<'03 Strategy'!E34,'03 Strategy'!E30/'03 Strategy'!E34,0)+IF(2029-2028<'03 Strategy'!F34,'03 Strategy'!F30/'03 Strategy'!F34,0)+IF(2029-2029<'03 Strategy'!G34,'03 Strategy'!G30/'03 Strategy'!G34,0)) -> -21008.333 | H39: =-(IF(2030-2027<'03 Strategy'!E34,'03 Strategy'!E30/'03 Strategy'!E34,0)+IF(2030-2028<'03 Strategy'!F34,'03 Strategy'!F30/'03 Strategy'!F34,0)+IF(2030-2029<'03 Strategy'!G34,'03 Strategy'!G30/'03 Strategy'!G34,0)+IF(2030-2030<'03 Strategy'!H34,'03 Strategy'!H30/'03 Strategy'!H34,0)) -> -24700
C40: Operating profit (EBIT) | D40: USD | E40: =E35+E39 -> 739077.8 | F40: =F35+F39 -> 6352846.3 | G40: =G35+G39 -> 15926223 | H40: =H35+H39 -> 24281534
C41: Profit before tax | D41: USD | E41: =E40 -> 739077.8 | F41: =F40 -> 6352846.3 | G41: =G40 -> 15926223 | H41: =H40 -> 24281534
C42: Provisional corporate income tax | D42: USD | E42: =-(MAX(0,SUM($E40:E40))-0)*'03 Strategy'!E35 -> -147815.56 | F42: =-(MAX(0,SUM($E40:F40))-MAX(0,SUM($E40:E40)))*'03 Strategy'!F35 -> -1270569.3 | G42: =-(MAX(0,SUM($E40:G40))-MAX(0,SUM($E40:F40)))*'03 Strategy'!G35 -> -3185244.6 | H42: =-(MAX(0,SUM($E40:H40))-MAX(0,SUM($E40:G40)))*'03 Strategy'!H35 -> -4856306.9
C43: NET PROFIT AFTER TAX | D43: USD | E43: =SUM(E41:E42) -> 591262.24 | F43: =SUM(F41:F42) -> 5082277 | G43: =SUM(G41:G42) -> 12740978 | H43: =SUM(H41:H42) -> 19425227

Sheet 06 Cash Flow
C2: ValueBridge | Projected Operating & Investing Cash Flow
C3: USD · 2027–2030 · indirect method
C4: Based on currently available data; excludes financing cash flows and cash balances. Cash collected on behalf of and remitted to brands is pass-through and excluded from FCF.
C6: Line item | D6: Unit | E6: 2027 | F6: 2028 | G6: 2029 | H6: 2030 | J6: Notes
C8: 01 CASH FLOW FROM OPERATING ACTIVITIES
C9: Net profit after tax (per model) | D9: USD | E9: ='05 P&L'!E43 -> 591262.24 | F9: ='05 P&L'!F43 -> 5082277 | G9: ='05 P&L'!G43 -> 12740978 | H9: ='05 P&L'!H43 -> 19425227
C10: Add back depreciation | D10: USD | E10: =-'05 P&L'!E39 -> 4133.3333 | F10: =-'05 P&L'!F39 -> 10783.333 | G10: =-'05 P&L'!G39 -> 21008.333 | H10: =-'05 P&L'!H39 -> 24700
C11: (Increase) / decrease in service fee receivables | D11: USD | E11: =E26 -> -118209.9 | F11: =F26 -> -324442.01 | G11: =G26 -> -930915.94 | H11: =H26 -> -692278.2
C12: (Increase) / decrease in brand fee reimbursement receivables | D12: USD | E12: =E28 -> -37187.553 | F12: =F28 -> -73083.872 | G12: =G28 -> -245178.07 | H12: =H28 -> -179146.54
C14: Net cash flow from operating activities | D14: USD | E14: =SUM(E9:E13) -> 439998.12 | F14: =SUM(F9:F13) -> 4695534.5 | G14: =SUM(G9:G13) -> 11585893 | H14: =SUM(H9:H13) -> 18578503
C16: 02 CASH FLOW FROM INVESTING ACTIVITIES
C17: Purchase of fixed assets | D17: USD | E17: =E40 -> -12400 | F17: =F40 -> -19950 | G17: =G40 -> -30675 | H17: =H40 -> -23475
C18: Net cash flow from investing activities | D18: USD | E18: =E17 -> -12400 | F18: =F17 -> -19950 | G18: =G17 -> -30675 | H18: =H17 -> -23475
C20: Cash flow after operating & investing (model FCF) | D20: USD | E20: =SUM(E14,E18) -> 427598.12 | F20: =SUM(F14,F18) -> 4675584.5 | G20: =SUM(G14,G18) -> 11555218 | H20: =SUM(H14,H18) -> 18555028
C22: Check: brand advances tie to change in receivables | D22: USD | E22: =ROUND(E12-E34,2) -> 0 | F22: =ROUND(F12-F34,2) -> 0 | G22: =ROUND(G12-G34,2) -> 0 | H22: =ROUND(H12-H34,2) -> 0
C24: 03 RECEIVABLES & WORKING CAPITAL
C25: Service fee receivables, year-end | D25: USD | E25: =(('05 P&L'!E11)*'01 Market'!E27*'03 Strategy'!E37+('05 P&L'!E11)*(1-'01 Market'!E27)*'03 Strategy'!E38+('05 P&L'!E12+'05 P&L'!E13)*'03 Strategy'!E39)/('01 Market'!E8*365/12) -> 118209.9 | F25: =(('05 P&L'!F11)*'01 Market'!F27*'03 Strategy'!F37+('05 P&L'!F11)*(1-'01 Market'!F27)*'03 Strategy'!F38+('05 P&L'!F12+'05 P&L'!F13)*'03 Strategy'!F39)/('01 Market'!F8*365/12) -> 442651.91 | G25: =(('05 P&L'!G11)*'01 Market'!G27*'03 Strategy'!G37+('05 P&L'!G11)*(1-'01 Market'!G27)*'03 Strategy'!G38+('05 P&L'!G12+'05 P&L'!G13)*'03 Strategy'!G39)/('01 Market'!G8*365/12) -> 1373567.9 | H25: =(('05 P&L'!H11)*'01 Market'!H27*'03 Strategy'!H37+('05 P&L'!H11)*(1-'01 Market'!H27)*'03 Strategy'!H38+('05 P&L'!H12+'05 P&L'!H13)*'03 Strategy'!H39)/('01 Market'!H8*365/12) -> 2065846.1
C26: Change in service fee receivables | D26: USD | E26: =-E25 -> -118209.9 | F26: =E25-F25 -> -324442.01 | G26: =F25-G25 -> -930915.94 | H26: =G25-H25 -> -692278.2
C27: Brand fee reimbursement receivables, year-end | D27: USD | E27: =('04 Operations'!E26*'03 Strategy'!E37+'04 Operations'!E27*'03 Strategy'!E38)/('01 Market'!E8*365/12) -> 37187.553 | F27: =('04 Operations'!F26*'03 Strategy'!F37+'04 Operations'!F27*'03 Strategy'!F38)/('01 Market'!F8*365/12) -> 110271.42 | G27: =('04 Operations'!G26*'03 Strategy'!G37+'04 Operations'!G27*'03 Strategy'!G38)/('01 Market'!G8*365/12) -> 355449.49 | H27: =('04 Operations'!H26*'03 Strategy'!H37+'04 Operations'!H27*'03 Strategy'!H38)/('01 Market'!H8*365/12) -> 534596.03
C28: Change in brand fee reimbursement receivables | D28: USD | E28: =-E27 -> -37187.553 | F28: =E27-F27 -> -73083.872 | G28: =F27-G27 -> -245178.07 | H28: =G27-H27 -> -179146.54
C30: 04 ADVANCES ON BEHALF OF BRANDS
C31: B2B logistics fees advanced | D31: USD | E31: =-'04 Operations'!E26 -> -170298.95 | F31: =-'04 Operations'!F26 -> -1009967.4 | G31: =-'04 Operations'!G26 -> -2365263.2 | H31: =-'04 Operations'!H26 -> -3557355.8
C32: B2C channel fees advanced | D32: USD | E32: =-'04 Operations'!E27 -> -239680 | F32: =-'04 Operations'!F27 -> -1421435.6 | G32: =-'04 Operations'!G27 -> -3328888.9 | H32: =-'04 Operations'!H27 -> -5006648.9
C33: Cash recovered from brands | D33: USD | E33: =-SUM(E31:E32)-E27 -> 372791.39 | F33: =-SUM(F31:F32)+E27-F27 -> 2358319.1 | G33: =-SUM(G31:G32)+F27-G27 -> 5448974 | H33: =-SUM(H31:H32)+G27-H27 -> 8384858.1
C34: Net cash flow from brand advances | D34: USD | E34: =SUM(E31:E33) -> -37187.553 | F34: =SUM(F31:F33) -> -73083.872 | G34: =SUM(G31:G33) -> -245178.07 | H34: =SUM(H31:H33) -> -179146.54
C36: 05 B2C RETURNS (memo, not a cash flow)
C37: B2C returned goods handed back to brands (in goods) | D37: USD | E37: ='04 Operations'!E24 -> 526126.83 | F37: ='04 Operations'!F24 -> 3120224.4 | G37: ='04 Operations'!G24 -> 7307317.1 | H37: ='04 Operations'!H24 -> 10990205 | J37: Returned goods come back and are handed to brands; no ValueBridge cash flow arises. Buyer refunds are already netted in sales after returns.
C39: 06 CAPEX & FCF
C40: Capital expenditure (CAPEX) | D40: USD | E40: =-'03 Strategy'!E30 -> -12400 | F40: =-'03 Strategy'!F30 -> -19950 | G40: =-'03 Strategy'!G30 -> -30675 | H40: =-'03 Strategy'!H30 -> -23475
C41: Cumulative FCF from 2027 | D41: USD | E41: =E20 -> 427598.12 | F41: =E41+F20 -> 5103182.6 | G41: =F41+G20 -> 16658400 | H41: =G41+H20 -> 35213428
C42: Peak funding requirement at year-end | D42: USD | E42: =-MIN(0,$E$41:$H$41) -> 0
C43: Payback year | D43: year | E43: =IF(E41>=0,2027,IF(F41>=0,2028,IF(G41>=0,2029,IF(H41>=0,2030,"After 2030")))) -> 2027
C45: 07 MEMO: CASH COLLECTED ON BEHALF OF BRANDS (outside FCF)
C46: Collected cash not yet remitted to brands, year-end | D46: USD | E46: ='04 Operations'!E30*'03 Strategy'!E40/('01 Market'!E8*365/12) -> 377179.4 | F46: ='04 Operations'!F30*'03 Strategy'!F40/('01 Market'!F8*365/12) -> 1118441.7 | G46: ='04 Operations'!G30*'03 Strategy'!G40/('01 Market'!G8*365/12) -> 2619301.4 | H46: ='04 Operations'!H30*'03 Strategy'!H40/('01 Market'!H8*365/12) -> 3939429.3 | J46: Sales proceeds collected from buyers/marketplaces but not yet due for remittance to brands (= payments to brands × settlement days ÷ selling days). This is brands' money (a payable) and is not used to fund the business.
C47: Change in collected cash during the year | D47: USD | E47: =E46 -> 377179.4 | F47: =F46-E46 -> 741262.29 | G47: =G46-F46 -> 1500859.7 | H47: =H46-G46 -> 1320127.9 | J47: Raises the year-end cash balance but is NOT added to FCF or the funding requirement in rows 21 and 44–46.

Sheet 08 Scenarios
C2: ValueBridge | Independent Scenarios by Driver
C3: Select a level for each driver in column J. Brand drivers are grouped together, followed by sales headcount, B2B and B2C.
C4: Eight scenario drivers; Vietnam customers are modelled as a % rate, Thailand brands as counts from the CREA plan.
C6: Line item | D6: Unit | E6: 2027 | F6: 2028 | G6: 2029 | H6: 2030 | J6: Select level
C8: 01 VIETNAM BRANDS
C9: Prospective customers selected for rollout in Vietnam | D9: % | E9: =INDEX(E10:E12,MATCH($J$9,$C$10:$C$12,0)) -> 0 | F9: =INDEX(F10:F12,MATCH($J$9,$C$10:$C$12,0)) -> 0.5 | G9: =INDEX(G10:G12,MATCH($J$9,$C$10:$C$12,0)) -> 0.7 | H9: =INDEX(H10:H12,MATCH($J$9,$C$10:$C$12,0)) -> 0.8 | J9: Base
C10: Conservative | F10: 0.375 | G10: 0.525 | H10: 0.6
C11: Base | F11: 0.5 | G11: 0.7 | H11: 0.8
C12: Optimistic | F12: 0.6 | G12: 0.8 | H12: 0.85
C14: 02 THAILAND BRANDS
C15: Thailand brands | D15: brands | E15: =INDEX(E16:E18,MATCH($J$15,$C$16:$C$18,0)) -> 0 | F15: =INDEX(F16:F18,MATCH($J$15,$C$16:$C$18,0)) -> 0 | G15: =INDEX(G16:G18,MATCH($J$15,$C$16:$C$18,0)) -> 30 | H15: =INDEX(H16:H18,MATCH($J$15,$C$16:$C$18,0)) -> 50 | J15: Base
C16: Conservative | E16: 0 | F16: 0 | G16: =ROUND(G17*75%,0) -> 23 | H16: =ROUND(H17*75%,0) -> 38
C17: Base | E17: 0 | F17: 0 | G17: 30 | H17: 50
C18: Optimistic | E18: 0 | F18: 0 | G18: =ROUND(G17*125%,0) -> 38 | H18: =ROUND(H17*125%,0) -> 63
C20: 03 BRAND MIX
C21: Share of large brands (Group A) | D21: % | E21: =INDEX(E22:E24,MATCH($J$21,$C$22:$C$24,0)) -> 0.2 | F21: =INDEX(F22:F24,MATCH($J$21,$C$22:$C$24,0)) -> 0.2 | G21: =INDEX(G22:G24,MATCH($J$21,$C$22:$C$24,0)) -> 0.2 | H21: =INDEX(H22:H24,MATCH($J$21,$C$22:$C$24,0)) -> 0.2 | J21: Base
C22: Conservative | E22: 0.15 | F22: 0.15 | G22: 0.15 | H22: 0.15
C23: Base | E23: 0.2 | F23: 0.2 | G23: 0.2 | H23: 0.2
C24: Optimistic | E24: 0.25 | F24: 0.25 | G24: 0.25 | H24: 0.25
C26: 04 NON-ONPOINT BRAND SALES
C27: Sales staff closing non-OnPoint brands | D27: FTE | E27: =INDEX(E28:E30,MATCH($J$27,$C$28:$C$30,0)) -> 0 | F27: =INDEX(F28:F30,MATCH($J$27,$C$28:$C$30,0)) -> 10 | G27: =INDEX(G28:G30,MATCH($J$27,$C$28:$C$30,0)) -> 15 | H27: =INDEX(H28:H30,MATCH($J$27,$C$28:$C$30,0)) -> 20 | J27: Base
C28: Conservative | E28: 0 | F28: 8 | G28: 12 | H28: 16
C29: Base | E29: 0 | F29: 10 | G29: 15 | H29: 20
C30: Optimistic | E30: 0 | F30: 12 | G30: 18 | H30: 24
C32: 05 B2B CHANNEL MIX
C33: B2B share of net recovery | D33: % | E33: =INDEX(E34:E36,MATCH($J$33,$C$34:$C$36,0)) -> 0.6 | F33: =INDEX(F34:F36,MATCH($J$33,$C$34:$C$36,0)) -> 0.6 | G33: =INDEX(G34:G36,MATCH($J$33,$C$34:$C$36,0)) -> 0.6 | H33: =INDEX(H34:H36,MATCH($J$33,$C$34:$C$36,0)) -> 0.6 | J33: Base
C34: Conservative | E34: 0.7 | F34: 0.7 | G34: 0.7 | H34: 0.7
C35: Base | E35: 0.6 | F35: 0.6 | G35: 0.6 | H35: 0.6
C36: Optimistic | E36: 0.5 | F36: 0.5 | G36: 0.5 | H36: 0.5
C38: 06 B2B UPLIFT OVER BASELINE
C39: B2B uplift over brand baseline | D39: % | E39: =INDEX(E40:E42,MATCH($J$39,$C$40:$C$42,0)) -> 0.35 | F39: =INDEX(F40:F42,MATCH($J$39,$C$40:$C$42,0)) -> 0.35 | G39: =INDEX(G40:G42,MATCH($J$39,$C$40:$C$42,0)) -> 0.35 | H39: =INDEX(H40:H42,MATCH($J$39,$C$40:$C$42,0)) -> 0.35 | J39: Base
C40: Conservative | E40: 0.2 | F40: 0.2 | G40: 0.2 | H40: 0.2
C41: Base | E41: 0.35 | F41: 0.35 | G41: 0.35 | H41: 0.35
C42: Optimistic | E42: 0.5 | F42: 0.5 | G42: 0.5 | H42: 0.5
C44: 07 B2C UPLIFT OVER BASELINE
C45: B2C uplift over brand baseline | D45: % | E45: =INDEX(E46:E48,MATCH($J$45,$C$46:$C$48,0)) -> 0.75 | F45: =INDEX(F46:F48,MATCH($J$45,$C$46:$C$48,0)) -> 0.75 | G45: =INDEX(G46:G48,MATCH($J$45,$C$46:$C$48,0)) -> 0.75 | H45: =INDEX(H46:H48,MATCH($J$45,$C$46:$C$48,0)) -> 0.75 | J45: Base
C46: Conservative | E46: 0.5 | F46: 0.5 | G46: 0.5 | H46: 0.5
C47: Base | E47: 0.75 | F47: 0.75 | G47: 0.75 | H47: 0.75
C48: Optimistic | E48: 0.85 | F48: 0.85 | G48: 0.85 | H48: 0.85
C50: 08 B2C RETURN RATE
C51: B2C returns / sales before returns | D51: % | E51: =INDEX(E52:E54,MATCH($J$51,$C$52:$C$54,0)) -> 0.18 | F51: =INDEX(F52:F54,MATCH($J$51,$C$52:$C$54,0)) -> 0.18 | G51: =INDEX(G52:G54,MATCH($J$51,$C$52:$C$54,0)) -> 0.18 | H51: =INDEX(H52:H54,MATCH($J$51,$C$52:$C$54,0)) -> 0.18 | J51: Base
C52: Conservative | E52: 0.25 | F52: 0.25 | G52: 0.25 | H52: 0.25
C53: Base | E53: 0.18 | F53: 0.18 | G53: 0.18 | H53: 0.18
C54: Optimistic | E54: 0.12 | F54: 0.12 | G54: 0.12 | H54: 0.12
C56: 09 RESULTS UNDER ACTIVE SCENARIO
C57: Active brands at year-end | D57: brands | E57: ='01 Market'!E15 -> 60 | F57: ='01 Market'!F15 -> 367 | G57: ='01 Market'!G15 -> 633 | H57: ='01 Market'!H15 -> 871
C58: Net recovery | D58: USD | E58: ='04 Operations'!E10 -> 5392800 | F58: ='04 Operations'!F10 -> 31982300 | G58: ='04 Operations'!G10 -> 74900000 | H58: ='04 Operations'!H10 -> 112649600
C59: Net revenue | D59: USD | E59: ='05 P&L'!E17 -> 1037817.6 | F59: ='05 P&L'!F17 -> 7351230.8 | G59: ='05 P&L'!G17 -> 17984967 | H59: ='05 P&L'!H17 -> 27198190
C60: EBITDA (excl. VAS direct costs) | D60: USD | E60: ='05 P&L'!E35 -> 743211.14 | F60: ='05 P&L'!F35 -> 6363629.6 | G60: ='05 P&L'!G35 -> 15947231 | H60: ='05 P&L'!H35 -> 24306234
C61: Net profit after tax | D61: USD | E61: ='05 P&L'!E43 -> 591262.24 | F61: ='05 P&L'!F43 -> 5082277 | G61: ='05 P&L'!G43 -> 12740978 | H61: ='05 P&L'!H43 -> 19425227
C62: Cash flow after operating & investing (FCF) | D62: USD | E62: ='06 Cash Flow'!E20 -> 427598.12 | F62: ='06 Cash Flow'!F20 -> 4675584.5 | G62: ='06 Cash Flow'!G20 -> 11555218 | H62: ='06 Cash Flow'!H20 -> 18555028
C64: Conservative/Optimistic assumptions for Thailand brands, external sales, B2B mix and B2C returns can be edited on each scenario row. The handover rate stays as in the base model.

Sheet 09 Checks
C2: ValueBridge | Model Checks
C3: "PASS" cells confirm reconciliations within the model; they do not validate input data or the EBITDA margin warning in row 24.
C5: Line item | D5: Unit | E5: 2027 | F5: 2028 | G5: 2029 | H5: 2030 | J5: Definition / source / notes
C8: 01 BRAND PROTECTION & FEE CAP
C9: B2B: brand proceeds ≥ baseline (difference, USD) | D9: USD | E9: ='04 Operations'!E11-'05 P&L'!E8-'04 Operations'!E15 -> 389480 | F9: ='04 Operations'!F11-'05 P&L'!F8-'04 Operations'!F15 -> 2309832.8 | G9: ='04 Operations'!G11-'05 P&L'!G8-'04 Operations'!G15 -> 5409444.4 | H9: ='04 Operations'!H11-'05 P&L'!H8-'04 Operations'!H15 -> 8135804.4 | J9: Must be ≥ 0: after ValueBridge fees, the brand still receives at least its own disposal option.
C10: B2C: brand proceeds ≥ baseline (difference, USD) | D10: USD | E10: ='04 Operations'!E12-'05 P&L'!E9-'04 Operations'!E17 -> 570096 | F10: ='04 Operations'!F12-'05 P&L'!F9-'04 Operations'!F17 -> 3380986 | G10: ='04 Operations'!G12-'05 P&L'!G9-'04 Operations'!G17 -> 7918000 | H10: ='04 Operations'!H12-'05 P&L'!H9-'04 Operations'!H17 -> 11908672
C11: Success fee / net recovery ≤ cap | D11: status | E11: =IF('05 P&L'!E19<='02 Fee Schedule'!E10+0.0001,"PASS","OVER CAP") -> PASS | F11: =IF('05 P&L'!F19<='02 Fee Schedule'!F10+0.0001,"PASS","OVER CAP") -> PASS | G11: =IF('05 P&L'!G19<='02 Fee Schedule'!G10+0.0001,"PASS","OVER CAP") -> PASS | H11: =IF('05 P&L'!H19<='02 Fee Schedule'!H10+0.0001,"PASS","OVER CAP") -> PASS
C13: 02 CONSISTENCY
C14: Revenue equals sum of four revenue lines (difference) | D14: USD | E14: ='05 P&L'!E17-('05 P&L'!E11+'05 P&L'!E12+'05 P&L'!E13+'05 P&L'!E16) -> 0 | F14: ='05 P&L'!F17-('05 P&L'!F11+'05 P&L'!F12+'05 P&L'!F13+'05 P&L'!F16) -> 0 | G14: ='05 P&L'!G17-('05 P&L'!G11+'05 P&L'!G12+'05 P&L'!G13+'05 P&L'!G16) -> 0 | H14: ='05 P&L'!H17-('05 P&L'!H11+'05 P&L'!H12+'05 P&L'!H13+'05 P&L'!H16) -> 0
C15: Net recovery equals B2B + B2C (difference) | D15: USD | E15: ='04 Operations'!E10-'04 Operations'!E11-'04 Operations'!E12 -> 0 | F15: ='04 Operations'!F10-'04 Operations'!F11-'04 Operations'!F12 -> 0 | G15: ='04 Operations'!G10-'04 Operations'!G11-'04 Operations'!G12 -> 0 | H15: ='04 Operations'!H10-'04 Operations'!H11-'04 Operations'!H12 -> 0
C16: B2B share between 0% and 100% | D16: status | E16: =IF(AND('01 Market'!E27>=0,'01 Market'!E27<=1),"PASS","ERROR") -> PASS | F16: =IF(AND('01 Market'!F27>=0,'01 Market'!F27<=1),"PASS","ERROR") -> PASS | G16: =IF(AND('01 Market'!G27>=0,'01 Market'!G27<=1),"PASS","ERROR") -> PASS | H16: =IF(AND('01 Market'!H27>=0,'01 Market'!H27<=1),"PASS","ERROR") -> PASS
C18: 03 REASONABLENESS WARNINGS
C19: Active brands ÷ projected OnPoint portfolio | D19: x | E19: ='01 Market'!E15/'01 Market'!E11 -> 0.125 | F19: ='01 Market'!F15/'01 Market'!F11 -> 0.63715278 | G19: ='01 Market'!G15/'01 Market'!G11 -> 0.91606368 | H19: ='01 Market'!H15/'01 Market'!H11 -> 1.0506634 | J19: Denominator is the projected OnPoint brand count for each year on 01 Market row 14. Numerator includes external and Thailand brands; a ratio above 100% can occur when expanding beyond the OnPoint portfolio.
C20: EBITDA margin reasonableness check | D20: status | E20: =IF('05 P&L'!E36>0.6,"REVIEW (>60%)","PASS") -> REVIEW (>60%) | F20: =IF('05 P&L'!F36>0.6,"REVIEW (>60%)","PASS") -> REVIEW (>60%) | G20: =IF('05 P&L'!G36>0.6,"REVIEW (>60%)","PASS") -> REVIEW (>60%) | H20: =IF('05 P&L'!H36>0.6,"REVIEW (>60%)","PASS") -> REVIEW (>60%)
C22: 04 SUMMARY
C23: Overall status | D23: status | E23: =IF(AND(E9>=0,E10>=0,E11="PASS",ABS(E14)<1,ABS(E15)<1,E16="PASS",E30="PASS",E34="PASS",E40="PASS",E44="PASS"),"PASS","CHECK") -> PASS | F23: =IF(AND(F9>=0,F10>=0,F11="PASS",ABS(F14)<1,ABS(F15)<1,F16="PASS",F30="PASS",F34="PASS",F40="PASS",F44="PASS"),"PASS","CHECK") -> PASS | G23: =IF(AND(G9>=0,G10>=0,G11="PASS",ABS(G14)<1,ABS(G15)<1,G16="PASS",G30="PASS",G34="PASS",G40="PASS",G44="PASS"),"PASS","CHECK") -> PASS | H23: =IF(AND(H9>=0,H10>=0,H11="PASS",ABS(H14)<1,ABS(H15)<1,H16="PASS",H30="PASS",H34="PASS",H40="PASS",H44="PASS"),"PASS","CHECK") -> PASS
C25: 05 RECONCILIATION OF BRAND-BORNE FEES & ADVANCES
C26: Total fees advanced = B2B fees + B2C fees (difference) | D26: USD | E26: ='04 Operations'!E25-'04 Operations'!E26-'04 Operations'!E27 -> 0 | F26: ='04 Operations'!F25-'04 Operations'!F26-'04 Operations'!F27 -> 0 | G26: ='04 Operations'!G25-'04 Operations'!G26-'04 Operations'!G27 -> 0 | H26: ='04 Operations'!H25-'04 Operations'!H26-'04 Operations'!H27 -> 0
C27: Recovery after fees ties to net target (difference) | D27: USD | E27: ='04 Operations'!E28-'04 Operations'!E10 -> 0 | F27: ='04 Operations'!F28-'04 Operations'!F10 -> 0 | G27: ='04 Operations'!G28-'04 Operations'!G10 -> 0 | H27: ='04 Operations'!H28-'04 Operations'!H10 -> 0
C28: Payments to brands tie after success fee (difference) | D28: USD | E28: ='04 Operations'!E30-('04 Operations'!E10-'04 Operations'!E29) -> 0 | F28: ='04 Operations'!F30-('04 Operations'!F10-'04 Operations'!F29) -> 0 | G28: ='04 Operations'!G30-('04 Operations'!G10-'04 Operations'!G29) -> 0 | H28: ='04 Operations'!H30-('04 Operations'!H10-'04 Operations'!H29) -> 0
C29: Advance cash flows tie to change in receivables (difference) | D29: USD | E29: ='06 Cash Flow'!E34+'06 Cash Flow'!E27 -> 0 | F29: ='06 Cash Flow'!F34+'06 Cash Flow'!F27-'06 Cash Flow'!E27 -> -6.5483619e-11 | G29: ='06 Cash Flow'!G34+'06 Cash Flow'!G27-'06 Cash Flow'!F27 -> -4.6566129e-10 | H29: ='06 Cash Flow'!H34+'06 Cash Flow'!H27-'06 Cash Flow'!G27 -> -5.8207661e-10 | J29: Advanced and reimbursed fees are pass-through cash flows; a receivable from brands remains at year-end equal to the unsettled balance.
C30: Brand-borne fee reconciliation status | D30: status | E30: =IF(AND(ABS(E26)<1,ABS(E27)<1,ABS(E28)<1,ABS(E29)<1),"PASS","CHECK") -> PASS | F30: =IF(AND(ABS(F26)<1,ABS(F27)<1,ABS(F28)<1,ABS(F29)<1),"PASS","CHECK") -> PASS | G30: =IF(AND(ABS(G26)<1,ABS(G27)<1,ABS(G28)<1,ABS(G29)<1),"PASS","CHECK") -> PASS | H30: =IF(AND(ABS(H26)<1,ABS(H27)<1,ABS(H28)<1,ABS(H29)<1),"PASS","CHECK") -> PASS
C32: 06 B2C RETURNS
C33: B2C sales before returns − returns = after returns | D33: USD | E33: ='04 Operations'!E23-'04 Operations'!E24-'04 Operations'!E22 -> 0 | F33: ='04 Operations'!F23-'04 Operations'!F24-'04 Operations'!F22 -> 0 | G33: ='04 Operations'!G23-'04 Operations'!G24-'04 Operations'!G22 -> 0 | H33: ='04 Operations'!H23-'04 Operations'!H24-'04 Operations'!H22 -> 0
C34: B2C returns reconciliation status | D34: status | E34: =IF(AND(ABS(E33)<1,ABS(E35)<1),"PASS","CHECK") -> PASS | F34: =IF(AND(ABS(F33)<1,ABS(F35)<1),"PASS","CHECK") -> PASS | G34: =IF(AND(ABS(G33)<1,ABS(G35)<1),"PASS","CHECK") -> PASS | H34: =IF(AND(ABS(H33)<1,ABS(H35)<1),"PASS","CHECK") -> PASS
C35: Returns handed back to brands equal returned B2C lot value (difference) | D35: USD | E35: ='04 Operations'!E31-'04 Operations'!E24 -> 0 | F35: ='04 Operations'!F31-'04 Operations'!F24 -> 0 | G35: ='04 Operations'!G31-'04 Operations'!G24 -> 0 | H35: ='04 Operations'!H31-'04 Operations'!H24 -> 0
C37: 07 MEGA SALE KOC BOOKING | J37: Checks the fixed per-session booking cost; does not infer affiliate commission from total B2C.
C38: Calendar × KOCs × cast fee ties to operating cost | D38: USD | E38: ='04 Operations'!E35*'03 Strategy'!E17*'03 Strategy'!E24-'04 Operations'!E38 -> 0 | F38: ='04 Operations'!F35*'03 Strategy'!F17*'03 Strategy'!F24-'04 Operations'!F38 -> 0 | G38: ='04 Operations'!G35*'03 Strategy'!G17*'03 Strategy'!G24-'04 Operations'!G38 -> 0 | H38: ='04 Operations'!H35*'03 Strategy'!H17*'03 Strategy'!H24-'04 Operations'!H38 -> 0 | J38: 03 Strategy × number of events = 04 Operations row 40.
C39: P&L booking cost ties to operating schedule | D39: USD | E39: ='05 P&L'!E33+'04 Operations'!E38 -> 0 | F39: ='05 P&L'!F33+'04 Operations'!F38 -> 0 | G39: ='05 P&L'!G33+'04 Operations'!G38 -> 0 | H39: ='05 P&L'!H33+'04 Operations'!H38 -> 0 | J39: P&L expense must equal the negative of the operating booking cost.
C40: KOC booking reconciliation status | D40: status | E40: =IF(AND(ABS(E38)<1,ABS(E39)<1),"PASS","CHECK") -> PASS | F40: =IF(AND(ABS(F38)<1,ABS(F39)<1),"PASS","CHECK") -> PASS | G40: =IF(AND(ABS(G38)<1,ABS(G39)<1),"PASS","CHECK") -> PASS | H40: =IF(AND(ABS(H38)<1,ABS(H39)<1),"PASS","CHECK") -> PASS | J40: PASS when both differences are zero.
C42: 08 RETURNS HANDLING COSTS
C43: P&L returns cost ties to operations (difference) | D43: USD | E43: ='05 P&L'!E21+'04 Operations'!E43 -> 0 | F43: ='05 P&L'!F21+'04 Operations'!F43 -> 0 | G43: ='05 P&L'!G21+'04 Operations'!G43 -> 0 | H43: ='05 P&L'!H21+'04 Operations'!H43 -> 0 | J43: P&L expense must equal the negative of total returns handling cost on 04 Operations row 45.
C44: Returns cost reconciliation status | D44: status | E44: =IF(ABS(E43)<1,"PASS","CHECK") -> PASS | F44: =IF(ABS(F43)<1,"PASS","CHECK") -> PASS | G44: =IF(ABS(G43)<1,"PASS","CHECK") -> PASS | H44: =IF(ABS(H43)<1,"PASS","CHECK") -> PASS
